{"name":"Make You Feel Better","artist":"Red Hot Chilli Peppers","level":"easy","tags":[""],"chords":[{"name":"C","key":"C","strings":"0 3 2 0 1 0","fingers":"x 4 3 x 2 x"},{"name":"D","key":"D","strings":"x x 0 2 3 2","fingers":"x x x 3 5 4"},{"name":"G","key":"G","strings":"3 2 0 0 0 3","fingers":"2 3 x x x 4"},{"name":"Em","key":"Em","strings":"0 2 2 0 0 0","fingers":"x 3 4 x x x"},{"name":"Bm","key":"Bm","strings":"x 2 4 4 3 2","fingers":"x 2 4 5 3 2"},{"name":"Am","key":"Am","strings":"x 0 2 2 1 0","fingers":"x x 3 4 2 x"}],"html":"<div class=\"section intro\"><h3>Intro</h3><div class=\"line\">Em Bm C G (2x)</div><div class=\"line\"></div></div><div class=\"section verse\"><h3>Verse</h3><div class=\"line\"><div class=\"chords\"><div is=\"chord\" name=\"Em\"></div></div>She's the one, she's the <div class=\"chords\"><div is=\"chord\" name=\"Bm\"></div></div>only one</div><div class=\"line\"><div class=\"chords\"><div is=\"chord\" name=\"C\"></div></div>She's got ripped back light, <div class=\"chords\"><div is=\"chord\" name=\"G\"></div></div>Gonna make me come</div><div class=\"line\">I say, <div class=\"chords\"><div is=\"chord\" name=\"Em\"></div></div>when I smile, I'm a<div class=\"chords\"><div is=\"chord\" name=\"Bm\"></div></div> really smile</div><div class=\"line\">I got <div class=\"chords\"><div is=\"chord\" name=\"C\"></div></div>dreams so wide, like a <div class=\"chords\"><div is=\"chord\" name=\"G\"></div></div>country mile</div><div class=\"line\">I said <div class=\"chords\"><div is=\"chord\" name=\"Em\"></div></div>now, I'll <div class=\"chords\"><div is=\"chord\" name=\"Bm\"></div></div>take it</div><div class=\"line\">It's <div class=\"chords\"><div is=\"chord\" name=\"C\"></div></div>better for <div class=\"chords\"><div is=\"chord\" name=\"G\"></div></div>you</div><div class=\"line\">Some<div class=\"chords\"><div is=\"chord\" name=\"Em\"></div></div>how, we'll <div class=\"chords\"><div is=\"chord\" name=\"Bm\"></div></div>make it</div><div class=\"line\">'cause <div class=\"chords\"><div is=\"chord\" name=\"C\"></div></div>that's what we <div class=\"chords\"><div is=\"chord\" name=\"G\"></div></div>do</div><div class=\"line\"></div></div><div class=\"section verse\"><h3>Verse</h3><div class=\"line\"><div class=\"chords\"><div is=\"chord\" name=\"Em\"></div></div>Pick a star in the <div class=\"chords\"><div is=\"chord\" name=\"Bm\"></div></div>open sky</div><div class=\"line\"><div class=\"chords\"><div is=\"chord\" name=\"C\"></div></div>I see you see me, and <div class=\"chords\"><div is=\"chord\" name=\"G\"></div></div>that is why I</div><div class=\"line\"><div class=\"chords\"><div is=\"chord\" name=\"Em\"></div></div>Hop along to the <div class=\"chords\"><div is=\"chord\" name=\"Bm\"></div></div>cowboy beat</div><div class=\"line\">When <div class=\"chords\"><div is=\"chord\" name=\"C\"></div></div>I feel your fire, jump <div class=\"chords\"><div is=\"chord\" name=\"G\"></div></div>up to meet</div><div class=\"line\">I said <div class=\"chords\"><div is=\"chord\" name=\"Em\"></div></div>now, I'll <div class=\"chords\"><div is=\"chord\" name=\"Bm\"></div></div>take it</div><div class=\"line\">It's <div class=\"chords\"><div is=\"chord\" name=\"C\"></div></div>better for <div class=\"chords\"><div is=\"chord\" name=\"G\"></div></div>you</div><div class=\"line\"><div class=\"chords\"><div is=\"chord\" name=\"Em\"></div></div>Somehow, we'll <div class=\"chords\"><div is=\"chord\" name=\"Bm\"></div></div>make it</div><div class=\"line\">'cause <div class=\"chords\"><div is=\"chord\" name=\"C\"></div></div>that's what we <div class=\"chords\"><div is=\"chord\" name=\"G\"></div></div>do</div><div class=\"line\"></div></div><div class=\"section chorus\"><h3>Chorus</h3><div class=\"line\"><div class=\"chords\"><div is=\"chord\" name=\"G\"></div></div>Something out <div class=\"chords\"><div is=\"chord\" name=\"D\"></div></div>there</div><div class=\"line\">Where <div class=\"chords\"><div is=\"chord\" name=\"Em\"></div></div>love is your <div class=\"chords\"><div is=\"chord\" name=\"C\"></div></div>only friend and</div><div class=\"line\"><div class=\"chords\"><div is=\"chord\" name=\"G\"></div></div>We are the <div class=\"chords\"><div is=\"chord\" name=\"D\"></div></div>ones</div><div class=\"line\">That will <div class=\"chords\"><div is=\"chord\" name=\"Em\"></div></div>make you feel <div class=\"chords\"><div is=\"chord\" name=\"C\"></div></div>better and</div><div class=\"line\"><div class=\"chords\"><div is=\"chord\" name=\"G\"></div></div>Someone to <div class=\"chords\"><div is=\"chord\" name=\"D\"></div></div>spare</div><div class=\"line\">When <div class=\"chords\"><div is=\"chord\" name=\"Em\"></div></div>love is the only <div class=\"chords\"><div is=\"chord\" name=\"C\"></div></div>end and</div><div class=\"line\"><div class=\"chords\"><div is=\"chord\" name=\"G\"></div></div>We are the <div class=\"chords\"><div is=\"chord\" name=\"D\"></div></div>ones</div><div class=\"line\">That <div class=\"chords\"><div is=\"chord\" name=\"Em\"></div></div>will make you feel <div class=\"chords\"><div is=\"chord\" name=\"C\"></div></div>better</div><div class=\"line\"></div></div><div class=\"section verse\"><h3>Verse</h3><div class=\"line\"><div class=\"chords\"><div is=\"chord\" name=\"G\"></div></div>In a world tha<div class=\"chords\"><div is=\"chord\" name=\"D\"></div></div>t has run amok</div><div class=\"line\">I've g<div class=\"chords\"><div is=\"chord\" name=\"Em\"></div></div>ot to set my <div class=\"chords\"><div is=\"chord\" name=\"C\"></div></div>sights just to get struck</div><div class=\"line\"><div class=\"chords\"><div is=\"chord\" name=\"G\"></div></div>I walk away fr<div class=\"chords\"><div is=\"chord\" name=\"D\"></div></div>om the rank and file</div><div class=\"line\">With a<div class=\"chords\"><div is=\"chord\" name=\"Em\"></div></div> punched out <div class=\"chords\"><div is=\"chord\" name=\"C\"></div></div>mouth and a pack of style</div><div class=\"line\"><div class=\"chords\"><div is=\"chord\" name=\"G\"></div></div>I say, she's t<div class=\"chords\"><div is=\"chord\" name=\"D\"></div></div>he one she's the only one</div><div class=\"line\">Make m<div class=\"chords\"><div is=\"chord\" name=\"Em\"></div></div>e search myse<div class=\"chords\"><div is=\"chord\" name=\"C\"></div></div>lf until I'm done, and</div><div class=\"line\"><div class=\"chords\"><div is=\"chord\" name=\"G\"></div></div>Tell me now in<div class=\"chords\"><div is=\"chord\" name=\"D\"></div></div> a telegram</div><div class=\"line\">Do the<div class=\"chords\"><div is=\"chord\" name=\"Em\"></div></div> sea of stars<div class=\"chords\"><div is=\"chord\" name=\"C\"></div></div> make a diagram, and</div><div class=\"line\"></div></div><div class=\"section chorus\"><h3>Chorus</h3><div class=\"line\"><div class=\"chords\"><div is=\"chord\" name=\"G\"></div></div>Something out <div class=\"chords\"><div is=\"chord\" name=\"D\"></div></div>there</div><div class=\"line\">Where <div class=\"chords\"><div is=\"chord\" name=\"Em\"></div></div>love is your <div class=\"chords\"><div is=\"chord\" name=\"C\"></div></div>only friend and</div><div class=\"line\"><div class=\"chords\"><div is=\"chord\" name=\"G\"></div></div>We are the <div class=\"chords\"><div is=\"chord\" name=\"D\"></div></div>ones</div><div class=\"line\">That will <div class=\"chords\"><div is=\"chord\" name=\"Em\"></div></div>make you feel <div class=\"chords\"><div is=\"chord\" name=\"C\"></div></div>better and</div><div class=\"line\"><div class=\"chords\"><div is=\"chord\" name=\"G\"></div></div>Someone to <div class=\"chords\"><div is=\"chord\" name=\"D\"></div></div>spare</div><div class=\"line\">When <div class=\"chords\"><div is=\"chord\" name=\"Em\"></div></div>love is the only <div class=\"chords\"><div is=\"chord\" name=\"C\"></div></div>end and</div><div class=\"line\"><div class=\"chords\"><div is=\"chord\" name=\"G\"></div></div>We are the <div class=\"chords\"><div is=\"chord\" name=\"D\"></div></div>ones</div><div class=\"line\">That <div class=\"chords\"><div is=\"chord\" name=\"Em\"></div></div>will make you feel <div class=\"chords\"><div is=\"chord\" name=\"C\"></div></div>better</div><div class=\"line\"></div></div><div class=\"section bridge\"><h3>Bridge</h3><div class=\"line\"><div class=\"chords\"><div is=\"chord\" name=\"D\"></div></div>Oh... <div class=\"chords\"><div is=\"chord\" name=\"Em\"></div></div>Yeah.. <div class=\"chords\"><div is=\"chord\" name=\"C\"></div></div>Yeah... <div class=\"chords\"><div is=\"chord\" name=\"Am\"></div></div>Yeah... <div class=\"chords\"><div is=\"chord\" name=\"C\"></div></div>Yeah</div><div class=\"line\"></div></div><div class=\"section verse\"><h3>Verse</h3><div class=\"line\"><div class=\"chords\"><div is=\"chord\" name=\"Em\"></div></div>So alive I arri<div class=\"chords\"><div is=\"chord\" name=\"Bm\"></div></div>ve on dust</div><div class=\"line\">You can<div class=\"chords\"><div is=\"chord\" name=\"C\"></div></div> search my mind<div class=\"chords\"><div is=\"chord\" name=\"G\"></div></div> for the red on rust, I said</div><div class=\"line\"><div class=\"chords\"><div is=\"chord\" name=\"Em\"></div></div>Take me there a<div class=\"chords\"><div is=\"chord\" name=\"Bm\"></div></div>nd she really cares</div><div class=\"line\">Lights <div class=\"chords\"><div is=\"chord\" name=\"C\"></div></div>up for me gonna<div class=\"chords\"><div is=\"chord\" name=\"G\"></div></div> hear my prayers</div><div class=\"line\"><div class=\"chords\"><div is=\"chord\" name=\"Em\"></div></div>I said now, I'l<div class=\"chords\"><div is=\"chord\" name=\"Bm\"></div></div>l take it</div><div class=\"line\">It's be<div class=\"chords\"><div is=\"chord\" name=\"C\"></div></div>tter for you   <div class=\"chords\"><div is=\"chord\" name=\"G\"></div></div></div><div class=\"line\"><div class=\"chords\"><div is=\"chord\" name=\"Em\"></div></div>Somehow, we'll <div class=\"chords\"><div is=\"chord\" name=\"Bm\"></div></div>make it</div><div class=\"line\">'cause <div class=\"chords\"><div is=\"chord\" name=\"C\"></div></div>that's what we <div class=\"chords\"><div is=\"chord\" name=\"G\"></div></div>do</div><div class=\"line\"></div></div><div class=\"section chorus\"><h3>Chorus</h3><div class=\"line\"><div class=\"chords\"><div is=\"chord\" name=\"G\"></div></div>Something out <div class=\"chords\"><div is=\"chord\" name=\"D\"></div></div>there</div><div class=\"line\">Where <div class=\"chords\"><div is=\"chord\" name=\"Em\"></div></div>love is your <div class=\"chords\"><div is=\"chord\" name=\"C\"></div></div>only friend and</div><div class=\"line\"><div class=\"chords\"><div is=\"chord\" name=\"G\"></div></div>We are the <div class=\"chords\"><div is=\"chord\" name=\"D\"></div></div>ones</div><div class=\"line\">That will <div class=\"chords\"><div is=\"chord\" name=\"Em\"></div></div>make you feel <div class=\"chords\"><div is=\"chord\" name=\"C\"></div></div>better and</div><div class=\"line\"><div class=\"chords\"><div is=\"chord\" name=\"G\"></div></div>Someone to <div class=\"chords\"><div is=\"chord\" name=\"D\"></div></div>spare</div><div class=\"line\">When <div class=\"chords\"><div is=\"chord\" name=\"Em\"></div></div>love is the only <div class=\"chords\"><div is=\"chord\" name=\"C\"></div></div>end and</div><div class=\"line\"><div class=\"chords\"><div is=\"chord\" name=\"G\"></div></div>We are the <div class=\"chords\"><div is=\"chord\" name=\"D\"></div></div>ones</div><div class=\"line\">That <div class=\"chords\"><div is=\"chord\" name=\"Em\"></div></div>will make you feel <div class=\"chords\"><div is=\"chord\" name=\"C\"></div></div>better</div><div class=\"line\"></div></div><div class=\"section outro\"><h3>Outro (4x)</h3><div class=\"line\"><div class=\"chords\"><div is=\"chord\" name=\"G\"></div></div>We are the <div class=\"chords\"><div is=\"chord\" name=\"D\"></div></div>ones,</div><div class=\"line\">that <div class=\"chords\"><div is=\"chord\" name=\"Em\"></div></div>will make you feel <div class=\"chords\"><div is=\"chord\" name=\"C\"></div></div>better</div></div>"}