{"name":"Už to nenapravím","artist":"Jaroslav Samson Lenk","level":"easy","chords":[{"name":"A","key":"A","strings":"0 0 2 0 2 0","fingers":"x x 3 x 5 x"},{"name":"E7","key":"E7","strings":"0 2 0 1 0 0","fingers":"x 2 x 1 x x"},{"name":"D","key":"D","strings":"x x 0 2 3 2","fingers":"x x x 3 5 4"},{"name":"E","key":"E","strings":"0 2 2 1 0 0","fingers":"x 3 4 2 x x"},{"name":"F","key":"F","strings":"1 3 3 2 1 1","fingers":"2 4 5 3 2 2"},{"name":"G","key":"G","strings":"3 2 0 0 0 3","fingers":"2 3 x x x 4"},{"name":"Dm","key":"Dm","strings":"x x 0 2 3 1","fingers":"x x x 3 4 2"},{"name":"Am","key":"Am","strings":"x 0 2 2 1 0","fingers":"x x 3 4 2 x"}],"html":"<div class=\"section intro\"><h3>Intro</h3><div class=\"line\"><div class=\"chords\"><div is=\"chord\" name=\"Am\"></div><div is=\"chord\" name=\"D\"></div><div is=\"chord\" name=\"F\"></div><div is=\"chord\" name=\"E\"></div><div is=\"chord\" name=\"Am\"></div><div is=\"chord\" name=\"E\"></div><div is=\"chord\" name=\"Am\"></div><div is=\"chord\" name=\"D\"></div><div is=\"chord\" name=\"F\"></div><div is=\"chord\" name=\"E\"></div><div is=\"chord\" name=\"Am\"></div><div is=\"chord\" name=\"E\"></div></div></div><div class=\"line\"></div></div><div class=\"section verse\"><h3>Verse</h3><div class=\"line\">V <div class=\"chords\"><div is=\"chord\" name=\"Am\"></div></div>devět hodin dvacet pět<div class=\"chords\"><div is=\"chord\" name=\"D\"></div></div> mě opustilo štěstí</div><div class=\"line\">te<div class=\"chords\"><div is=\"chord\" name=\"F\"></div></div>n vlak co jsem jím měl jet na koleji dá<div class=\"chords\"><div is=\"chord\" name=\"E\"></div></div>vno ne<div class=\"chords\"><div is=\"chord\" name=\"E7\"></div></div>stál </div><div class=\"line\">v <div class=\"chords\"><div is=\"chord\" name=\"Am\"></div></div>devět hodin dvacet pět<div class=\"chords\"><div is=\"chord\" name=\"D\"></div></div> jako bych dostal pěstí</div><div class=\"line\">já<div class=\"chords\"><div is=\"chord\" name=\"F\"></div></div> za hodinu na náměstí měl jsem stát<div class=\"chords\"><div is=\"chord\" name=\"E\"></div></div> ale v<div class=\"chords\"><div is=\"chord\" name=\"E7\"></div></div> jiným městě.</div><div class=\"line\">Tv<div class=\"chords\"><div is=\"chord\" name=\"A\"></div></div>á zpráva zněla prostě a byla tak krátká</div><div class=\"line\">že<div class=\"chords\"><div is=\"chord\" name=\"Dm\"></div></div> stavíš se jen na skok že nechalas mi vrátka</div><div class=\"line\"><div class=\"chords\"><div is=\"chord\" name=\"G\"></div></div>zadní otevřená z<div class=\"chords\"><div is=\"chord\" name=\"E\"></div></div>adní otevřená </div><div class=\"line\">já<div class=\"chords\"><div is=\"chord\" name=\"A\"></div></div> naposled tě viděl když ti bylo dvacet</div><div class=\"line\">to<div class=\"chords\"><div is=\"chord\" name=\"Dm\"></div></div> jsi tenkrát řekla, že se nechceš vracet</div><div class=\"line\"><div class=\"chords\"><div is=\"chord\" name=\"G\"></div></div>že jsi unavená z<div class=\"chords\"><div is=\"chord\" name=\"E\"></div></div>e mě unavená. </div><div class=\"line\"></div></div><div class=\"section chorus\"><h3>Chorus</h3><div class=\"line\"><div class=\"chords\"><div is=\"chord\" name=\"Am\"></div><div is=\"chord\" name=\"D\"></div><div is=\"chord\" name=\"F\"></div><div is=\"chord\" name=\"E\"></div></div>Vap ta da...</div><div class=\"line\"></div></div><div class=\"section verse\"><h3>Verse</h3><div class=\"line\">Já<div class=\"chords\"><div is=\"chord\" name=\"Am\"></div></div> čekala jsem hlavu jako stře<div class=\"chords\"><div is=\"chord\" name=\"D\"></div></div>p a zdálo se, že dlouho</div><div class=\"line\">m<div class=\"chords\"><div is=\"chord\" name=\"F\"></div></div>ůže za to vinný sklep, že člověk často <div class=\"chords\"><div is=\"chord\" name=\"E\"></div></div>sleví <div class=\"chords\"><div is=\"chord\" name=\"E7\"></div></div></div><div class=\"line\">Já<div class=\"chords\"><div is=\"chord\" name=\"Am\"></div></div> čekala jsem hlavu jako stře<div class=\"chords\"><div is=\"chord\" name=\"D\"></div></div>p, s podvědomou touhou</div><div class=\"line\">č<div class=\"chords\"><div is=\"chord\" name=\"F\"></div></div>ekala jsem dobu dlouhou víc než dost, k<div class=\"chords\"><div is=\"chord\" name=\"E\"></div></div>olik p<div class=\"chords\"><div is=\"chord\" name=\"E7\"></div></div>řesně nevím</div><div class=\"line\">Pa<div class=\"chords\"><div is=\"chord\" name=\"A\"></div></div>k jedenáctá bila a už to bylo pasé</div><div class=\"line\">já<div class=\"chords\"><div is=\"chord\" name=\"Dm\"></div></div> měla vědět dřív, že vidět chci tě zase</div><div class=\"line\"><div class=\"chords\"><div is=\"chord\" name=\"G\"></div></div>láska nerezaví, <div class=\"chords\"><div is=\"chord\" name=\"E\"></div></div>láska nerezaví</div><div class=\"line\">Te<div class=\"chords\"><div is=\"chord\" name=\"A\"></div></div>n list co jsem ti psala byl dozajista hloupý</div><div class=\"line\">by<div class=\"chords\"><div is=\"chord\" name=\"Dm\"></div></div>l odměřený moc, na vlídný slovo skoupý</div><div class=\"line\"><div class=\"chords\"><div is=\"chord\" name=\"G\"></div></div>už to nenapravím<div class=\"chords\"><div is=\"chord\" name=\"E\"></div></div>, už to nenapravím</div><div class=\"line\"></div></div><div class=\"section chorus\"><h3>Chorus</h3><div class=\"line\"><div class=\"chords\"><div is=\"chord\" name=\"Am\"></div><div is=\"chord\" name=\"D\"></div><div is=\"chord\" name=\"F\"></div><div is=\"chord\" name=\"E\"></div></div>Vap ta da...</div></div>"}